{
  "db_name": "PostgreSQL",
  "query": "\n            UPDATE job_status \n            SET status = $1, updated_at = CURRENT_TIMESTAMP\n            WHERE user_id = $2\n            RETURNING *\n            ",
  "describe": {
    "columns": [
      {
        "ordinal": 0,
        "name": "id",
        "type_info": "Int4"
      },
      {
        "ordinal": 1,
        "name": "user_id",
        "type_info": "Int4"
      },
      {
        "ordinal": 2,
        "name": "role",
        "type_info": "Varchar"
      },
      {
        "ordinal": 3,
        "name": "branch_address",
        "type_info": "Varchar"
      },
      {
        "ordinal": 4,
        "name": "status",
        "type_info": "Varchar"
      },
      {
        "ordinal": 5,
        "name": "applied_at",
        "type_info": "Timestamp"
      },
      {
        "ordinal": 6,
        "name": "updated_at",
        "type_info": "Timestamp"
      }
    ],
    "parameters": {
      "Left": [
        "Varchar",
        "Int4"
      ]
    },
    "nullable": [
      false,
      false,
      false,
      false,
      false,
      false,
      false
    ]
  },
  "hash": "c762d31164020878038cf0309d1a0ff66100642c0737010645b0fbfc2db0d1df"
}
